daypack/__init__.py
daypack-0.0.0.dist-info/METADATA
daypack-0.0.0.dist-info/WHEEL
daypack-0.0.0.dist-info/top_level.txt
daypack-0.0.0.dist-info/RECORD
