Metadata-Version: 2.1
Name: daypack
Version: 0.0.0
Summary: Daypack: A rugged multisig wallet for everyday adventures
Author: ApeWorX LTD
Requires-Python: >=3.10
Requires-Dist: eth-ape>=0.8.37
